{
  "collapse-filter": false,
  "search": "",
  "showTags": false,
  "showAttachments": false,
  "hideUnresolved": false,
  "showOrphans": false,
  "collapse-color-groups": false,
  "colorGroups": [
    {
      "query": "索引",
      "color": {
        "a": 1,
        "rgb": 15090098
      }
    }
  ],
  "collapse-display": false,
  "showArrow": false,
  "textFadeMultiplier": 0,
  "nodeSizeMultiplier": 1,
  "lineSizeMultiplier": 1.001140625,
  "collapse-forces": false,
  "centerStrength": 0.518713248970312,
  "repelStrength": 10,
  "linkStrength": 1,
  "linkDistance": 362,
  "scale": 0.7357982402775839,
  "close": true
}